{
  "id": "1776843427903_65",
  "savedAt": "2026-04-22T07:37:07.903Z",
  "date": "2026-04-01",
  "author": "日高",
  "batch1": {
    "name": "モンシェリー(トリ)",
    "qty": "1290パック",
    "start": "09:00",
    "end": "14:30",
    "notes": "840パックが早く終わったので明日の,430パックまで製造終了しました。"
  },
  "batch2": {
    "name": "",
    "qty": "",
    "start": "",
    "end": "",
    "notes": ""
  },
  "batch3": {
    "name": "",
    "qty": "",
    "start": "",
    "end": "",
    "notes": ""
  },
  "semiProduct": "",
  "otherNotes": ""
}